cherrypicker/__about__.py
cherrypicker/__init__.py
cherrypicker/exceptions.py
cherrypicker/leaf.py
cherrypicker/picker.py
cherrypicker/traversable.py
cherrypicker/util.py
cherrypicker-0.2.1.dist-info/LICENSE
cherrypicker-0.2.1.dist-info/METADATA
cherrypicker-0.2.1.dist-info/WHEEL
cherrypicker-0.2.1.dist-info/top_level.txt
cherrypicker-0.2.1.dist-info/RECORD
